ebcommon/__init__.py
ebcommon/bufferio.py
ebcommon/models_buffer.py
ebcommon/models_common.py
ebcommon/models_job.py
ebcommon/models_mservice.py
ebcommon/models_policy.py
ebcommon/models_runtime.py
ebcommon/simple_runner.py
ebcommon-1.0.0.dist-info/licenses/LICENSE
ebcommon-1.0.0.dist-info/METADATA
ebcommon-1.0.0.dist-info/WHEEL
ebcommon-1.0.0.dist-info/top_level.txt
ebcommon-1.0.0.dist-info/RECORD
