Metadata-Version: 2.4
Name: ebcommon
Version: 1.0.0
Summary: Ephemeral buffer service Common model
Author-email: Laurent Morin <Laurent.Morin@irisa.fr>
Project-URL: Homepage, https://ebuffer.aqmo.org/api/documentation
Project-URL: Documentation, https://ebuffer.aqmo.org/api/documentation
Project-URL: Repository, https://ebuffer.aqmo.org/api/documentation
Project-URL: Issues, https://ebuffer.aqmo.org/api/documentation
Project-URL: Changelog, https://ebuffer.aqmo.org/api/documentation
Keywords: HPC,buffers,workflow,distributed
Classifier: License :: OSI Approved :: MIT License
Classifier: Programming Language :: Python :: 3.10
Classifier: Programming Language :: Python :: 3.12
Classifier: Operating System :: OS Independent
Classifier: Topic :: Scientific/Engineering
Classifier: Topic :: System :: Benchmark
Classifier: Topic :: System :: Distributed Computing
Requires-Python: >=3.10
License-File: LICENSE
Requires-Dist: pydantic>=2.10.6
Requires-Dist: Requests>=2.32.3
Provides-Extra: all
Provides-Extra: docs
Provides-Extra: dev
Dynamic: license-file
